menupal/__init__.py
menupal/preprocessing.py
menupal/recommend.py
menupal/recviz.py
menupal-0.1.3.dist-info/METADATA
menupal-0.1.3.dist-info/WHEEL
menupal-0.1.3.dist-info/top_level.txt
menupal-0.1.3.dist-info/RECORD
