Metadata-Version: 2.4
Name: menupal
Version: 0.1.3
Summary: Menu Recommendation Tool
Home-page: https://github.com/911218sky/mc-menu-picker
Author: sky
Author-email: sky@sky1218.com
Keywords: menu recommendation utils tool
Classifier: Programming Language :: Python :: 3.10
Classifier: Programming Language :: Python :: 3.11
Classifier: Programming Language :: Python :: 3.12
Classifier: Programming Language :: Python :: 3 :: Only
Classifier: License :: OSI Approved :: MIT License
Classifier: Operating System :: OS Independent
Requires-Python: >=3.10
Requires-Dist: matplotlib~=3.10.3
Requires-Dist: numpy~=2.2.6
Requires-Dist: openpyxl~=3.1.5
Requires-Dist: pandas~=2.2.3
Requires-Dist: scikit_learn~=1.6.1
Dynamic: author
Dynamic: author-email
Dynamic: classifier
Dynamic: description
Dynamic: description-content-type
Dynamic: home-page
Dynamic: keywords
Dynamic: requires-dist
Dynamic: requires-python
Dynamic: summary
